setup.py
scripts/twitterwatch
twitterwatch/__init__.py
twitterwatch/cliparse.py
twitterwatch/confparse.py
twitterwatch/emailwarning.py
twitterwatch/main.py
twitterwatch.egg-info/PKG-INFO
twitterwatch.egg-info/SOURCES.txt
twitterwatch.egg-info/dependency_links.txt
twitterwatch.egg-info/requires.txt
twitterwatch.egg-info/top_level.txt