Metadata-Version: 1.1
Name: twitterwatch
Version: 0.1
Summary: Twitter bot to watch a Twitter user timeline
Home-page: https://github.com/chaica/twitterwatch
Author: Carl Chenet
Author-email: chaica@ohmytux.com
License: GNU GPL v3
Download-URL: https://github.com/chaica/twitterwatch
Platform: UNKNOWN
Classifier: Intended Audience :: End Users/Desktop
Classifier: Environment :: Console
Classifier: License :: OSI Approved :: GNU General Public License (GPL)
Classifier: Operating System :: POSIX :: Linux
Classifier: Programming Language :: Python :: 3.4
